DLCD/week4/2/mux4to1.v
// Base 2:1 MUX Module
module mux2x1 (
    input wire a,
    input wire b,
    input wire s,
    output wire y
);
    assign y = s ? b : a;
endmodule

// Top-level 4:1 MUX Module
module mux4x1 (
    input wire I0,
    input wire I1,
    input wire I2,
    input wire I3,
    input wire S0,  // LSB
    input wire S1,  // MSB
    output wire f
);

    // Internal wires connecting the first stage to the second stage
    wire mux_top_out;
    wire mux_bot_out;

    // First Stage Instantiations
    // Top MUX (controlled by S0)
    mux2x1 M1 (
        .a(I0), 
        .b(I1), 
        .s(S0), 
        .y(mux_top_out)
    );

    // Bottom MUX (controlled by S0)
    mux2x1 M2 (
        .a(I2), 
        .b(I3), 
        .s(S0), 
        .y(mux_bot_out)
    );

    // Second Stage Instantiation
    // Final MUX (controlled by S1)
    mux2x1 M3 (
        .a(mux_top_out), 
        .b(mux_bot_out), 
        .s(S1), 
        .y(f)
    );

endmodule

DLCD/week4/2/mux4to1_tb.v
module mux4x1_tb;

    // Inputs
    reg I0, I1, I2, I3;
    reg S1, S0;

    // Outputs
    wire f;

    // Instantiate the Unit Under Test (UUT)
    mux4x1 uut (
        .I0(I0), 
        .I1(I1), 
        .I2(I2), 
        .I3(I3),
        .S0(S0), 
        .S1(S1),
        .f(f)
    );

    initial begin
        // Generate waveform file for GTKWave
        $dumpfile("mux4x1_waves.vcd");
        $dumpvars(0, mux4x1_tb);

        // --- TEST CASE 1 ---
        // Give inputs alternating values to easily track them
        I0 = 1; I1 = 0; I2 = 1; I3 = 0;
        
        $display("Testing Pattern: I0=%b, I1=%b, I2=%b, I3=%b", I0, I1, I2, I3);
        S1 = 0; S0 = 0; #10; // Selects I0 -> f should be 1
        S1 = 0; S0 = 1; #10; // Selects I1 -> f should be 0
        S1 = 1; S0 = 0; #10; // Selects I2 -> f should be 1
        S1 = 1; S0 = 1; #10; // Selects I3 -> f should be 0

        // --- TEST CASE 2 ---
        // Invert the inputs to ensure it's not a fluke
        I0 = 0; I1 = 1; I2 = 0; I3 = 1;
        
        $display("Testing Pattern: I0=%b, I1=%b, I2=%b, I3=%b", I0, I1, I2, I3);
        S1 = 0; S0 = 0; #10; // Selects I0 -> f should be 0
        S1 = 0; S0 = 1; #10; // Selects I1 -> f should be 1
        S1 = 1; S0 = 0; #10; // Selects I2 -> f should be 0
        S1 = 1; S0 = 1; #10; // Selects I3 -> f should be 1

        $finish;
    end

    // Monitor changes
    initial begin
        $monitor("Time=%0t | S1=%b S0=%b || Output f=%b", $time, S1, S0, f);
    end

endmodule

DLCD/week4/2/mux4x1_waves.vcd
$date
	Fri Aug 28 13:45:06 2026
$end
$version
	Icarus Verilog
$end
$timescale
	1s
$end
$scope module mux4x1_tb $end
$var wire 1 ! f $end
$var reg 1 " I0 $end
$var reg 1 # I1 $end
$var reg 1 $ I2 $end
$var reg 1 % I3 $end
$var reg 1 & S0 $end
$var reg 1 ' S1 $end
$scope module uut $end
$var wire 1 " I0 $end
$var wire 1 # I1 $end
$var wire 1 $ I2 $end
$var wire 1 % I3 $end
$var wire 1 & S0 $end
$var wire 1 ' S1 $end
$var wire 1 ( mux_top_out $end
$var wire 1 ) mux_bot_out $end
$var wire 1 ! f $end
$scope module M1 $end
$var wire 1 " a $end
$var wire 1 # b $end
$var wire 1 & s $end
$var wire 1 ( y $end
$upscope $end
$scope module M2 $end
$var wire 1 $ a $end
$var wire 1 % b $end
$var wire 1 & s $end
$var wire 1 ) y $end
$upscope $end
$scope module M3 $end
$var wire 1 ( a $end
$var wire 1 ) b $end
$var wire 1 ' s $end
$var wire 1 ! y $end
$upscope $end
$upscope $end
$upscope $end
$enddefinitions $end
$comment Show the parameter values. $end
$dumpall
$end
#0
$dumpvars
1)
1(
0'
0&
0%
1$
0#
1"
1!
$end
#10
0!
0(
0)
1&
#20
1!
1(
1)
0&
1'
#30
0!
0(
0)
1&
#40
0&
0'
1%
0$
1#
0"
#50
1!
1(
1)
1&
#60
0!
0(
0)
0&
1'
#70
1!
1(
1)
1&
