DLCD/week4/1/mux2to1.v
module mux2to1 (
    input wire i0,
    input wire i1,
    input wire j,
    output wire O
);

    // Using the ternary operator: if j is 1, O = i1; else O = i0
    assign O = j ? i1 : i0;

endmodule

DLCD/week4/1/mux2to1_tb.v
module mux2to1_tb;

    // Declare inputs as reg (registers can hold values)
    reg i0;
    reg i1;
    reg j;

    // Declare outputs as wire
    wire O;

    // Instantiate the multiplexer module
    mux2to1 uut (
        .i0(i0),
        .i1(i1),
        .j(j),
        .O(O)
    );

    initial begin
        // Generate waveform file for GTKWave
        $dumpfile("mux_waves.vcd");
        $dumpvars(0, mux2to1_tb);

        // Apply test vectors (all possible combinations of inputs)
        // Format: {j, i1, i0}
        
        // Select = 0 (Output should follow i0)
        j = 0; i1 = 0; i0 = 0; #10;
        j = 0; i1 = 0; i0 = 1; #10; 
        j = 0; i1 = 1; i0 = 0; #10;
        j = 0; i1 = 1; i0 = 1; #10;

        // Select = 1 (Output should follow i1)
        j = 1; i1 = 0; i0 = 0; #10;
        j = 1; i1 = 0; i0 = 1; #10;
        j = 1; i1 = 1; i0 = 0; #10;
        j = 1; i1 = 1; i0 = 1; #10;

        // End simulation
        $finish;
    end

    // Optional: Print to terminal to see values during simulation
    initial begin
        $monitor("Time=%0t | j=%b | i1=%b | i0=%b || O=%b", $time, j, i1, i0, O);
    end

endmodule

DLCD/week4/1/mux_waves.vcd
$date
	Fri Aug 28 13:39:14 2026
$end
$version
	Icarus Verilog
$end
$timescale
	1s
$end
$scope module mux2to1_tb $end
$var wire 1 ! O $end
$var reg 1 " i0 $end
$var reg 1 # i1 $end
$var reg 1 $ j $end
$scope module uut $end
$var wire 1 " i0 $end
$var wire 1 # i1 $end
$var wire 1 $ j $end
$var wire 1 ! O $end
$upscope $end
$upscope $end
$enddefinitions $end
$comment Show the parameter values. $end
$dumpall
$end
#0
$dumpvars
0$
0#
0"
0!
$end
#10
1!
1"
#20
0!
0"
1#
#30
1!
1"
#40
0!
0"
0#
1$
#50
1"
#60
1!
0"
1#
#70
1"
