DLCD/week2/fullladder.v
module xor1 (y,a,b);
input a,b;
output y;
assign y = a ^ b;
endmodule
module and1 (y,a,b);
input a,b;
output y;
assign y = a & b;
endmodule
module or1 (y,a,b);
input a,b;  
output y;
assign y = a | b;
endmodule
module full_adder (sum,carry,a,b,c);
input a,b,c;
output sum,carry;
wire w1,w2,w3;
xor1 a1(w1,a,b);
xor1 a2(sum,w1,c);
and1 a3(w2,w1,c);
and1 a4(w3,a,b);
or1 a5(carry,w2,w3);

endmodule

DLCD/week2/fulladder_tb.v
module fulladder_tb;
    wire sum, carry;
    reg a, b, c;
    full_adder fa1(sum, carry, a, b, c);

    initial
    begin
        #000000 a=0; b=0; c=0;
        #100 a=0; b=0; c=1;
        #100 a=0; b=1; c=0;
        #100 a=0; b=1; c=1;
        #100 a=1; b=0; c=0;
        #100 a=1; b=0; c=1;
        #100 a=1; b=1; c=0;
        #100 a=1; b=1; c=1;
    end
    initial
    begin
        $monitor($time, "a=%b, b=%b, c=%b, sum=%b, carry=%b", a, b, c, sum, carry);
    end
    initial
    begin
        $dumpfile("full_adder.vcd");
        $dumpvars(0, fulladder_tb);
    end
    
    
endmodule

DLCD/week2/full_adder.vcd
$date
	Fri Aug 21 15:06:18 2026
$end
$version
	Icarus Verilog
$end
$timescale
	1s
$end
$scope module fulladder_tb $end
$var wire 1 ! sum $end
$var wire 1 " carry $end
$var reg 1 # a $end
$var reg 1 $ b $end
$var reg 1 % c $end
$scope module fa1 $end
$var wire 1 # a $end
$var wire 1 $ b $end
$var wire 1 % c $end
$var wire 1 & w3 $end
$var wire 1 ' w2 $end
$var wire 1 ( w1 $end
$var wire 1 ! sum $end
$var wire 1 " carry $end
$scope module a1 $end
$var wire 1 # a $end
$var wire 1 $ b $end
$var wire 1 ( y $end
$upscope $end
$scope module a2 $end
$var wire 1 ( a $end
$var wire 1 % b $end
$var wire 1 ! y $end
$upscope $end
$scope module a3 $end
$var wire 1 ( a $end
$var wire 1 % b $end
$var wire 1 ' y $end
$upscope $end
$scope module a4 $end
$var wire 1 # a $end
$var wire 1 $ b $end
$var wire 1 & y $end
$upscope $end
$scope module a5 $end
$var wire 1 ' a $end
$var wire 1 & b $end
$var wire 1 " y $end
$upscope $end
$upscope $end
$upscope $end
$enddefinitions $end
$comment Show the parameter values. $end
$dumpall
$end
#0
$dumpvars
0(
0'
0&
0%
0$
0#
0"
0!
$end
#100
1!
1%
#200
1(
0%
1$
#300
1"
0!
1'
1%
#400
0"
1!
0'
0%
0$
1#
#500
1"
0!
1'
1%
#600
0'
0(
1&
0%
1$
#700
1!
1%
