DLCD/week3/two_stage_full_adder.v
`timescale 1ns/1ps

module full_adder (
    input wire a,
    input wire b,
    input wire cin,
    output wire sum,
    output wire cout
);
    assign sum = a ^ b ^ cin;
    assign cout = (a & b) | (b & cin) | (a & cin);
endmodule

// Block-diagram implementation:
// FA1 takes i1[2], i1[1], i1[0]
// FA2 takes i2, FA1 sum, FA1 carry
module two_stage_full_adder (
    input wire [2:0] i1,
    input wire i2,
    output wire Sum1,
    output wire Cout1
);
    wire s0;
    wire c0;

    full_adder fa1 (
        .a(i1[2]),
        .b(i1[1]),
        .cin(i1[0]),
        .sum(s0),
        .cout(c0)
    );

    full_adder fa2 (
        .a(i2),
        .b(s0),
        .cin(c0),
        .sum(Sum1),
        .cout(Cout1)
    );
endmodule

DLCD/week3/two_stage_full_adder_tb.v
`timescale 1ns/1ps

module two_stage_full_adder_tb;
    reg [2:0] i1;
    reg i2;
    wire Sum1;
    wire Cout1;

    integer k;

    two_stage_full_adder dut (
        .i1(i1),
        .i2(i2),
        .Sum1(Sum1),
        .Cout1(Cout1)
    );

    initial begin
        $dumpfile("two_stage_full_adder.vcd");
        $dumpvars(0, two_stage_full_adder_tb);

        i1 = 3'b000;
        i2 = 1'b0;
        #5;

        // Sweep all 16 input combinations (i2 + i1[2:0])
        for (k = 0; k < 16; k = k + 1) begin
            {i2, i1} = k[3:0];
            #10;
        end

        #10;
        $finish;
    end
endmodule

DLCD/week3/two_stage_full_adder.vcd
$date
	Fri Aug 21 20:40:24 2026
$end
$version
	Icarus Verilog
$end
$timescale
	1ps
$end
$scope module two_stage_full_adder_tb $end
$var wire 1 ! Sum1 $end
$var wire 1 " Cout1 $end
$var reg 3 # i1 [2:0] $end
$var reg 1 $ i2 $end
$var integer 32 % k [31:0] $end
$scope module dut $end
$var wire 3 & i1 [2:0] $end
$var wire 1 $ i2 $end
$var wire 1 ' s0 $end
$var wire 1 ( c0 $end
$var wire 1 ! Sum1 $end
$var wire 1 " Cout1 $end
$scope module fa1 $end
$var wire 1 ) a $end
$var wire 1 * b $end
$var wire 1 + cin $end
$var wire 1 ( cout $end
$var wire 1 ' sum $end
$upscope $end
$scope module fa2 $end
$var wire 1 $ a $end
$var wire 1 ' b $end
$var wire 1 ( cin $end
$var wire 1 " cout $end
$var wire 1 ! sum $end
$upscope $end
$upscope $end
$upscope $end
$enddefinitions $end
$comment Show the parameter values. $end
$dumpall
$end
#0
$dumpvars
0+
0*
0)
0(
0'
b0 &
bx %
0$
b0 #
0"
0!
$end
#5000
b0 %
#15000
1!
1'
1+
b1 #
b1 &
b1 %
#25000
1!
1'
1*
0+
b10 #
b10 &
b10 %
#35000
1(
0'
1+
b11 #
b11 &
b11 %
#45000
0"
0(
1'
1)
0*
0+
b100 #
b100 &
b100 %
#55000
1(
0'
1+
b101 #
b101 &
b101 %
#65000
1(
0'
1*
0+
b110 #
b110 &
b110 %
#75000
1"
0!
1'
1+
b111 #
b111 &
b111 %
#85000
0"
0(
1!
0'
0)
0*
0+
1$
b0 #
b0 &
b1000 %
#95000
1"
0!
1'
1+
b1 #
b1 &
b1001 %
#105000
1"
0!
1'
1*
0+
b10 #
b10 &
b1010 %
#115000
1(
0'
1+
b11 #
b11 &
b1011 %
#125000
0(
1'
1)
0*
0+
b100 #
b100 &
b1100 %
#135000
1(
0'
1+
b101 #
b101 &
b1101 %
#145000
1(
0'
1*
0+
b110 #
b110 &
b1110 %
#155000
1!
1'
1+
b111 #
b111 &
b1111 %
#165000
b10000 %
